{"version":"1.2","person":{"datePublished":"2023-11-08","name":"Robert De Thweng","nameForms":[{"lang":"en","fullText":"Robert De Thweng","parts":[{"type":"http://gedcomx.org/Given","value":"Robert"},{"type":"http://gedcomx.org/Surname","value":"De Thweng"}],"order":"EUROTYPIC"}],"gender":"Male","lifespan":"1109–1152","fullLifespan":"about 1109–about 1152","birthDate":"+1109","birthPlace":{"address":"Thweng, Yorkshire, England","geo":{"latitude":53.95878,"longitude":-1.08248,"@type":"GeoCoordinates"},"@type":"Place"},"deathDate":"+1152","deathPlace":{"address":"Legsby, Lincolnshire, England","geo":{"latitude":53.35,"longitude":-0.3,"@type":"GeoCoordinates"},"@type":"Place"},"events":[{"name":"Birth","sources":"0","year":"1109","date":"about 1109","place":"Thweng, Yorkshire, England"},{"name":"Death","sources":"0","year":"1152","date":"about 1152","place":"Legsby, Lincolnshire, England","age":"43"}],"spouse":[{"gender":"Unknown","@type":"Person","identifier":"UNKNOWN","url":"https://ancestors.familysearch.org/en/UNKNOWN/-","published":false}],"children":[{"name":"Robert FitzRobert or de Thweng","gender":"Male","lifespan":"1145–1246","birthDate":"A+1145","deathDate":"+1246","age":101,"otherParentId":"UNKNOWN","@type":"Person","identifier":"G6NZ-453","url":"https://ancestors.familysearch.org/en/G6NZ-453/robert-thweng-1145-1246","published":true}],"ageAtDeath":43,"@type":"Person","@context":"http://schema.org","identifier":"G2HX-91L","memories":0,"photos":0,"stories":0,"sources":0,"nameSources":0,"genderSources":0,"url":"https://ancestors.familysearch.org/en/G2HX-91L/robert-de-thweng-1109-1152"},"localizedData":{"sq":{"about 1109–about 1152":"rreth vitit 1109–rreth vitit 1152","1145–1246":"vitit1145–vitit1246","1109–1152":"vitit1109–vitit1152","about 1109":"rreth vitit 1109","1246":"vitit 1246","1145":"vitit 1145","1152":"vitit 1152","about 1152":"rreth vitit 1152","1109":"vitit 1109","Legsby, Lincolnshire, England":"Legsby, Lincolnshire, England","Thweng, Yorkshire, England":"Yorkshire, Anglia, Mbretëria e Bashkuar"},"hy":{"about 1109–about 1152":"about 1109–about 1152","1145–1246":"1145–1246","1109–1152":"1109–1152","about 1109":"about 1109","1246":"1246","1145":"1145","1152":"1152","about 1152":"about 1152","1109":"1109","Legsby, Lincolnshire, England":"Legsby, Lincolnshire, Անգլիա","Thweng, Yorkshire, England":"Yorkshire, Անգլիա, United Kingdom"},"bg":{"about 1109–about 1152":"около 1109 г.–около 1152 г.","1145–1246":"1145г.–1246г.","1109–1152":"1109г.–1152г.","about 1109":"около 1109 г.","1246":"1246 г.","1145":"1145 г.","1152":"1152 г.","about 1152":"около 1152 г.","1109":"1109 г.","Legsby, Lincolnshire, England":"легсби, линколншир, Англия","Thweng, Yorkshire, England":"еркшир, Англия, Обединено кралство"},"km":{"about 1109–about 1152":"ប្រហែល​ឆ្នាំ 1109–ប្រហែល​ឆ្នាំ 1152","1145–1246":"ឆ្នាំ1145–ឆ្នាំ1246","1109–1152":"ឆ្នាំ1109–ឆ្នាំ1152","about 1109":"ប្រហែល​ឆ្នាំ 1109","1246":"ឆ្នាំ 1246","1145":"ឆ្នាំ 1145","1152":"ឆ្នាំ 1152","about 1152":"ប្រហែល​ឆ្នាំ 1152","1109":"ឆ្នាំ 1109","Legsby, Lincolnshire, England":"ឡិហ្គsប៊ី, លីnកូលនស៊ីរe, ប្រទេសអង់គ្លេស","Thweng, Yorkshire, England":"យ៉ុរកស៊ីរe, ប្រទេសអង់គ្លេស, uណៃteត គីnហ្គដុម"},"ceb":{"about 1109–about 1152":"mga 1109–mga 1152","1145–1246":"1145–1246","1109–1152":"1109–1152","about 1109":"mga 1109","1246":"1246","1145":"1145","1152":"1152","about 1152":"mga 1152","1109":"1109","Legsby, Lincolnshire, England":"Legsby, Lincolnshire, England","Thweng, Yorkshire, England":"Yorkshire, England, United Kingdom"},"zh":{"about 1109–about 1152":"大約1109年–大約1152年","1145–1246":"1145年–1246年","1109–1152":"1109年–1152年","about 1109":"大約1109年","1246":"1246年","1145":"1145年","1152":"1152年","about 1152":"大約1152年","1109":"1109年","Legsby, Lincolnshire, England":"英國林可爾史爾萊格斯比","Thweng, Yorkshire, England":"英國英格蘭越可爾","lifeSummary":"Robert De Thweng於大約1109年出生在英國英格蘭越可爾。他至少有1個兒子。他去世於大約1152年在英國林可爾史爾萊格斯比享年45歲。"},"zh-hans":{"about 1109–about 1152":"大约1109年–大约1152年","1145–1246":"1145年–1246年","1109–1152":"1109年–1152年","about 1109":"大约1109年","1246":"1246年","1145":"1145年","1152":"1152年","about 1152":"大约1152年","1109":"1109年","Legsby, Lincolnshire, England":"英国林可爾史爾萊格斯比","Thweng, Yorkshire, England":"英国英格兰越可爾","lifeSummary":"Robert De Thweng于大约1109年出生在英国英格兰越可爾。他至少有1个儿子。他去世于大约1152年在英国林可爾史爾萊格斯比享年45岁。"},"hr":{"about 1109–about 1152":"oko 1109.–oko 1152.","1145–1246":"1145–1246","1109–1152":"1109–1152","about 1109":"oko 1109.","1246":"1246","1145":"1145","1152":"1152","about 1152":"oko 1152.","1109":"1109","Legsby, Lincolnshire, England":"Legsby, Lincolnshire, England","Thweng, Yorkshire, England":"Yorkshire, Engleska, United Kingdom"},"cs":{"about 1109–about 1152":"okolo 1109–okolo 1152","1145–1246":"1145–1246","1109–1152":"1109–1152","about 1109":"okolo 1109","1246":"1246","1145":"1145","1152":"1152","about 1152":"okolo 1152","1109":"1109","Legsby, Lincolnshire, England":"Legsby, Lincolnshire, Anglie","Thweng, Yorkshire, England":"Yorkshire, Anglie, United Kingdom"},"da":{"about 1109–about 1152":"omkring 1109–omkring 1152","1145–1246":"1145–1246","1109–1152":"1109–1152","about 1109":"omkring 1109","1246":"1246","1145":"1145","1152":"1152","about 1152":"omkring 1152","1109":"1109","Legsby, Lincolnshire, England":"Legsby, Lincolnshire, England","Thweng, Yorkshire, England":"Jórvík, England, United Kingdom"},"nl":{"about 1109–about 1152":"circa 1109–circa 1152","1145–1246":"1145–1246","1109–1152":"1109–1152","about 1109":"circa 1109","1246":"1246","1145":"1145","1152":"1152","about 1152":"circa 1152","1109":"1109","Legsby, Lincolnshire, England":"Legsby, Lincolnshire, England","Thweng, Yorkshire, England":"Yorkshire, Engeland, Verenigd Koninkrijk"},"en":{"about 1109–about 1152":"about 1109–about 1152","1145–1246":"1145–1246","1109–1152":"1109–1152","about 1109":"about 1109","1246":"1246","1145":"1145","1152":"1152","about 1152":"about 1152","1109":"1109","Legsby, Lincolnshire, England":"Legsby, Lincolnshire, England","Thweng, Yorkshire, England":"Yorkshire, England, United Kingdom","nameMeanings":[{"name":"De","type":"LAST","attribution":"Dictionary of American Family Names © Patrick Hanks 2003, 2006.","meanings":["Some characteristic forenames:  Indian Dilip, Anirban, Gopal, Alok, Anindya, Arunava, Asit, Asok, Dibyendu, Goutam, Indra, Indranil.","Indian: variant of   Dey  ."],"variants":[{"name":"Dey","meanings":["Some characteristic forenames:  Indian Ashit, Indu, Naina, Partha, Soumya, Ajit, Anjan, Anjana, Anup, Arjun, Arun, Ashim.","English, Scottish, and Welsh: variant of   Day  .","German: topographic name from a field name in North Rhine-Westphalia, denoting a sizeable piece of land, from Middle Low German <i>dē</i> ‘thigh’ (referring to the shape of the property)."]}]},{"name":"Thweng","type":"LAST","attribution":"Dictionary of American Family Names © Patrick Hanks 2003, 2006.","meanings":["English: habitational name from a place so called in East Yorkshire, named with Old Norse <i>thvengr</i> or Old English <i>thweng</i> ‘narrow strip of land’.","History: Martha Thwing (died 1774) is buried in the King's Chapel Burying Ground in Boston MA."],"variants":[]},{"name":"Robert","type":"FIRST","attribution":"Dictionary of First Names © Patrick Hanks and Flavia Hodges 1990, 2003, 2006.","meanings":["One of the many French names of Germanic origin that were introduced into Britain by the Normans; it has since remained in continuous use. It is derived from the nearly synonymous elements <i>hrōd</i> ‘fame’ + <i>berht</i> ‘bright, famous’, and had a native Old English predecessor of similar form (<i>Hreodbeorht</i>), which was supplanted by the Norman name. Two dukes of Normandy in the 11th century bore the name: the father of  William the Conqueror  (sometimes identified with the legendary Robert the Devil), and his eldest son. It was borne also by three kings of Scotland, notably  Robert the Bruce  (  1274–1329 ), who freed Scotland from English domination. The altered short form <i>Bob</i> is very common, but <i>Hob</i> and <i>Dob</i>, which were common in the Middle Ages and gave rise to surnames, are extinct.  See also  Rupert ."],"variants":[]}],"lifeSummary":"Robert De Thweng was born about 1109, in Yorkshire, England, United Kingdom. He had at least 1 son. He died about 1152, in Legsby, Lincolnshire, England, at the age of 45."},"et":{"about 1109–about 1152":"umbes 1109–umbes 1152","1145–1246":"1145–1246","1109–1152":"1109–1152","about 1109":"umbes 1109","1246":"1246","1145":"1145","1152":"1152","about 1152":"umbes 1152","1109":"1109","Legsby, Lincolnshire, England":"Legsby, Lincolnshire, England","Thweng, Yorkshire, England":"Yorkshire, Inglismaa, United Kingdom"},"fi":{"about 1109–about 1152":"noin 1109–noin 1152","1145–1246":"1145–1246","1109–1152":"1109–1152","about 1109":"noin 1109","1246":"1246","1145":"1145","1152":"1152","about 1152":"noin 1152","1109":"1109","Legsby, Lincolnshire, England":"Legsby, Lincolnshire, England","Thweng, Yorkshire, England":"Yorkshire, Englanti, Yhdistynyt kuningaskunta"},"fr":{"about 1109–about 1152":"environ 1109–environ 1152","1145–1246":"1145–1246","1109–1152":"1109–1152","about 1109":"environ 1109","1246":"1246","1145":"1145","1152":"1152","about 1152":"environ 1152","1109":"1109","Legsby, Lincolnshire, England":"Legsby, Lincolnshire, Angleterre","Thweng, Yorkshire, England":"Everwyck, Angleterre, Royaume-Uni","lifeSummary":"Robert De Thweng est né environ 1109, à Everwyck, Angleterre, Royaume-Uni. Il a eu au moins 1 fils. Il est décédé environ 1152, à Legsby, Lincolnshire, Angleterre, à l’âge de 45 ans."},"de":{"about 1109–about 1152":"um 1109–um 1152","1145–1246":"1145–1246","1109–1152":"1109–1152","about 1109":"um 1109","1246":"1246","1145":"1145","1152":"1152","about 1152":"um 1152","1109":"1109","Legsby, Lincolnshire, England":"Legsby, Lincolnshire, England","Thweng, Yorkshire, England":"Yorkshire, England, United Kingdom","lifeSummary":"Robert De Thweng wurde um 1109 in Yorkshire, England, United Kingdom geboren. Er hatte mindestens 1 Sohn. Er starb um 1152 im Alter von 45 Jahren in Legsby, Lincolnshire, England."},"ht":{"about 1109–about 1152":"about 1109–about 1152","1145–1246":"1145–1246","1109–1152":"1109–1152","about 1109":"about 1109","1246":"1246","1145":"1145","1152":"1152","about 1152":"about 1152","1109":"1109","Legsby, Lincolnshire, England":"Legsby, Lincolnshire, England","Thweng, Yorkshire, England":"Yorkshire, Angletè, United Kingdom"},"hu":{"about 1109–about 1152":"1109 körül–1152 körül","1145–1246":"1145–1246","1109–1152":"1109–1152","about 1109":"1109 körül","1246":"1246","1145":"1145","1152":"1152","about 1152":"1152 körül","1109":"1109","Legsby, Lincolnshire, England":"Legsby, Lincolnshire, England","Thweng, Yorkshire, England":"Yorkshire, Anglia, United Kingdom"},"id":{"about 1109–about 1152":"sekitar 1109–sekitar 1152","1145–1246":"1145–1246","1109–1152":"1109–1152","about 1109":"sekitar 1109","1246":"1246","1145":"1145","1152":"1152","about 1152":"sekitar 1152","1109":"1109","Legsby, Lincolnshire, England":"Legsby, Lincolnshire, England","Thweng, Yorkshire, England":"Yorkshire, Inggris, United Kingdom"},"it":{"about 1109–about 1152":"circa 1109–circa 1152","1145–1246":"1145–1246","1109–1152":"1109–1152","about 1109":"circa 1109","1246":"1246","1145":"1145","1152":"1152","about 1152":"circa 1152","1109":"1109","Legsby, Lincolnshire, England":"Legsby, Lincolnshire, England","Thweng, Yorkshire, England":"Yorkshire, Inghilterra, Regno Unito","lifeSummary":"Robert De Thweng è nato il circa 1109 nel Yorkshire, Inghilterra, Regno Unito. Lui avuto almeno 1 figlio. Morì circa 1152, nel Legsby, Lincolnshire, England, all'età di 45 anni."},"ja":{"about 1109–about 1152":"約1109年–約1152年","1145–1246":"1145年–1246年","1109–1152":"1109年–1152年","about 1109":"約1109年","1246":"1246年","1145":"1145年","1152":"1152年","about 1152":"約1152年","1109":"1109年","Legsby, Lincolnshire, England":"イギリスリンコルンシュアイアレグスビー","Thweng, Yorkshire, England":"イギリスイギリスヨークシュアイア","lifeSummary":"Robert De Thwengは約1109年にイギリスイギリスヨークシュアイアで生まれた。彼は少なくとも1人の息子をもうけた。彼は約1152年にイギリスリンコルンシュアイアレグスビーで45歳で死去した。"},"ko":{"about 1109–about 1152":"대략 1109년–대략 1152년","1145–1246":"1145년–1246년","1109–1152":"1109년–1152년","about 1109":"대략 1109년","1246":"1246년","1145":"1145년","1152":"1152년","about 1152":"대략 1152년","1109":"1109년","Legsby, Lincolnshire, England":"영국 링코실르 레그스비","Thweng, Yorkshire, England":"영국 잉글랜드 요르크실르","lifeSummary":"Robert De Thweng(은)는 대략 1109년 영국 잉글랜드 요르크실르에서 태어났다. 그는 적어도 한 명의 아들을 두었다. 그는 대략 1152년 영국 링코실르 레그스비에서 45세의 나이로 사망했다."},"lv":{"about 1109–about 1152":"ap 1109. gadu–ap 1152. gadu","1145–1246":"1145–1246","1109–1152":"1109–1152","about 1109":"ap 1109. gadu","1246":"1246","1145":"1145","1152":"1152","about 1152":"ap 1152. gadu","1109":"1109","Legsby, Lincolnshire, England":"Legsby, Lincolnshire, England","Thweng, Yorkshire, England":"Yorkshire, Anglija, Lielbritānija"},"mg":{"about 1109–about 1152":"tany ho any amin'ny 1109–tany ho any amin'ny 1152","1145–1246":"1145–1246","1109–1152":"1109–1152","about 1109":"tany ho any amin'ny 1109","1246":"1246","1145":"1145","1152":"1152","about 1152":"tany ho any amin'ny 1152","1109":"1109","Legsby, Lincolnshire, England":"Legsby, Lincolnshire, England","Thweng, Yorkshire, England":"Yorkshire, Angletera, United Kingdom"},"ms":{"about 1109–about 1152":"kira–kira 1109–kira–kira 1152","1145–1246":"1145–1246","1109–1152":"1109–1152","about 1109":"kira-kira 1109","1246":"1246","1145":"1145","1152":"1152","about 1152":"kira-kira 1152","1109":"1109","Legsby, Lincolnshire, England":"Legsby, Lincolnshire, England","Thweng, Yorkshire, England":"Yorkshire, England, United Kingdom"},"mn":{"about 1109–about 1152":"ойролцоогоор 1109 он–ойролцоогоор 1152 он","1145–1246":"1145он–1246он","1109–1152":"1109он–1152он","about 1109":"ойролцоогоор 1109 он","1246":"1246 он","1145":"1145 он","1152":"1152 он","about 1152":"ойролцоогоор 1152 он","1109":"1109 он","Legsby, Lincolnshire, England":"Legsby, Lindon, Английн","Thweng, Yorkshire, England":"Eoferwic, Англи, Нэгдсэн Вант Улс"},"no":{"about 1109–about 1152":"rundt 1109–rundt 1152","1145–1246":"1145–1246","1109–1152":"1109–1152","about 1109":"rundt 1109","1246":"1246","1145":"1145","1152":"1152","about 1152":"rundt 1152","1109":"1109","Legsby, Lincolnshire, England":"Legsby, Lincolnshire, England","Thweng, Yorkshire, England":"Yorkshire, England, United Kingdom"},"pl":{"about 1109–about 1152":"około 1109 r.–około 1152 r.","1145–1246":"1145r.–1246r.","1109–1152":"1109r.–1152r.","about 1109":"około 1109 r.","1246":"1246 r.","1145":"1145 r.","1152":"1152 r.","about 1152":"około 1152 r.","1109":"1109 r.","Legsby, Lincolnshire, England":"Legsby, Lincolnshire, England","Thweng, Yorkshire, England":"Yorkshire, Anglia, United Kingdom"},"pt":{"about 1109–about 1152":"aproximadamente 1109–aproximadamente 1152","1145–1246":"1145–1246","1109–1152":"1109–1152","about 1109":"aproximadamente 1109","1246":"1246","1145":"1145","1152":"1152","about 1152":"aproximadamente 1152","1109":"1109","Legsby, Lincolnshire, England":"Legsby, Lincolnshire, Inglaterra","Thweng, Yorkshire, England":"Yorkshire, Inglaterra, United Kingdom","lifeSummary":"Robert De Thweng nasceu aproximadamente 1109, em Yorkshire, Inglaterra, United Kingdom. Ele teve pelo menos 1 filho. Ele faleceu aproximadamente 1152, em Legsby, Lincolnshire, Inglaterra, com 45 anos."},"ro":{"about 1109–about 1152":"aproximativ 1109–aproximativ 1152","1145–1246":"1145–1246","1109–1152":"1109–1152","about 1109":"aproximativ 1109","1246":"1246","1145":"1145","1152":"1152","about 1152":"aproximativ 1152","1109":"1109","Legsby, Lincolnshire, England":"Legsby, Lincolnshire, England","Thweng, Yorkshire, England":"Yorkshire, Anglia, United Kingdom"},"ru":{"about 1109–about 1152":"около 1109 г.–около 1152 г.","1145–1246":"1145г.–1246г.","1109–1152":"1109г.–1152г.","about 1109":"около 1109 г.","1246":"1246 г.","1145":"1145 г.","1152":"1152 г.","about 1152":"около 1152 г.","1109":"1109 г.","Legsby, Lincolnshire, England":"легсби, линколншир, Англия","Thweng, Yorkshire, England":"еркшир, Англия, Великобритания","lifeSummary":"Robert De Thweng родился около 1109 г. в местности еркшир, Англия, Великобритания. У него был по крайней мере 1 сын. Он умер около 1152 г. в местности легсби, линколншир, Англия в возрасте 45 лет."},"sm":{"about 1109–about 1152":"e tusa o le 1109–e tusa o le 1152","1145–1246":"1145–1246","1109–1152":"1109–1152","about 1109":"e tusa o le 1109","1246":"1246","1145":"1145","1152":"1152","about 1152":"e tusa o le 1152","1109":"1109","Legsby, Lincolnshire, England":"Legsby, Lincolnshire, Egelani","Thweng, Yorkshire, England":"Yorkshire, Egelani, United Kingdom"},"sk":{"about 1109–about 1152":"okolo 1109–okolo 1152","1145–1246":"1145–1246","1109–1152":"1109–1152","about 1109":"okolo 1109","1246":"1246","1145":"1145","1152":"1152","about 1152":"okolo 1152","1109":"1109","Legsby, Lincolnshire, England":"Legsby, Lincolnshire, England","Thweng, Yorkshire, England":"Yorkshire, Anglicko, Spojené kráľovstvo"},"es":{"about 1109–about 1152":"aproximadamente 1109–aproximadamente 1152","1145–1246":"1145–1246","1109–1152":"1109–1152","about 1109":"aproximadamente 1109","1246":"1246","1145":"1145","1152":"1152","about 1152":"aproximadamente 1152","1109":"1109","Legsby, Lincolnshire, England":"Legsby, Lincolnshire, Inglaterra","Thweng, Yorkshire, England":"Yorkshire, Inglaterra, Reino Unido","lifeSummary":"Robert De Thweng nació aproximadamente 1109, en Yorkshire, Inglaterra, Reino Unido. Tuvo por lo menos 1 hijo. Murió aproximadamente 1152, en Legsby, Lincolnshire, Inglaterra, a la edad de 45 años."},"sv":{"about 1109–about 1152":"omkring 1109–omkring 1152","1145–1246":"1145–1246","1109–1152":"1109–1152","about 1109":"omkring 1109","1246":"1246","1145":"1145","1152":"1152","about 1152":"omkring 1152","1109":"1109","Legsby, Lincolnshire, England":"Legsby, Lincolnshire, England","Thweng, Yorkshire, England":"Yorkshire, England, United Kingdom"},"tl":{"about 1109–about 1152":"mga 1109–mga 1152","1145–1246":"1145–1246","1109–1152":"1109–1152","about 1109":"mga 1109","1246":"1246","1145":"1145","1152":"1152","about 1152":"mga 1152","1109":"1109","Legsby, Lincolnshire, England":"Legsby, Lincolnshire, England","Thweng, Yorkshire, England":"Yorkshire, England, United Kingdom"},"th":{"about 1109–about 1152":"ประมาณปี 1109–ประมาณปี 1152","1145–1246":"ปี1145–ปี1246","1109–1152":"ปี1109–ปี1152","about 1109":"ประมาณปี 1109","1246":"ปี 1246","1145":"ปี 1145","1152":"ปี 1152","about 1152":"ประมาณปี 1152","1109":"ปี 1109","Legsby, Lincolnshire, England":"เลเอกสบี, ลินโกลนชิเร, เอิงแลนด์","Thweng, Yorkshire, England":"โยอรกชิเร, อังกฤษ, สหราชอาณาจักร"},"to":{"about 1109–about 1152":"taʻu 1109 nai–taʻu 1152 nai","1145–1246":"taʻu1145–taʻu1246","1109–1152":"taʻu1109–taʻu1152","about 1109":"taʻu 1109 nai","1246":"taʻu 1246","1145":"taʻu 1145","1152":"taʻu 1152","about 1152":"taʻu 1152 nai","1109":"taʻu 1109","Legsby, Lincolnshire, England":"Legsby, Lincolnshire, 'Ingilani","Thweng, Yorkshire, England":"Yorkshire, 'Ingilani, United Kingdom"},"uk":{"about 1109–about 1152":"прибл. 1109 р.–прибл. 1152 р.","1145–1246":"1145–1246","1109–1152":"1109–1152","about 1109":"прибл. 1109 р.","1246":"1246","1145":"1145","1152":"1152","about 1152":"прибл. 1152 р.","1109":"1109","Legsby, Lincolnshire, England":"легсби, линколншир, Англия","Thweng, Yorkshire, England":"еркшир, Англія, Великобританія"},"vi":{"about 1109–about 1152":"khoảng năm 1109–khoảng năm 1152","1145–1246":"năm1145–năm1246","1109–1152":"năm1109–năm1152","about 1109":"khoảng năm 1109","1246":"năm 1246","1145":"năm 1145","1152":"năm 1152","about 1152":"khoảng năm 1152","1109":"năm 1109","Legsby, Lincolnshire, England":"Legsby, Lincolnshire, England","Thweng, Yorkshire, England":"Yorkshire, Anh, Vương quốc Liên hiệp"}}}